{
  "gp": {
    "arena_size": 2048.0,
    "corridor_redundancy": 15.0,
    "flock_factor": 600.0,
    "main_room_thresh": 0.8,
    "min_separation_factor": 1.7,
    "model": "tinykeep",
    "room_szmax": 1024.0,
    "room_szmin": 512.0,
    "room_szratio": 1.8,
    "rooms": 16,
    "tan_fudge": 0.0001,
    "tile_snap_size": 4.0
  },
  "model": {
    "corridors": [
      {
        "join_sides": [
          3,
          1
        ],
        "joins": [
          1,
          0
        ],
        "points": [
          [
            -3396.6399300128733,
            -2457.3480475115684
          ],
          [
            365.654591616634,
            -2457.3480475115684
          ]
        ]
      },
      {
        "join_sides": [
          2,
          1
        ],
        "joins": [
          3,
          11
        ],
        "points": [
          [
            3471.1515717670063,
            3694.701467431225
          ],
          [
            3471.1515717670063,
            4302.022393730606
          ],
          [
            4483.250604347943,
            4302.022393730606
          ]
        ]
      },
      {
        "join_sides": [
          3,
          2
        ],
        "joins": [
          1,
          10
        ],
        "points": [
          [
            -3396.6399300128733,
            -2129.6406566096093
          ],
          [
            -2431.439048201214,
            -2129.6406566096093
          ],
          [
            -2431.439048201214,
            -1303.0598646488625
          ]
        ]
      },
      {
        "join_sides": [
          3,
          0
        ],
        "joins": [
          10,
          8
        ],
        "points": [
          [
            -1573.439048201214,
            -1619.0598646488625
          ],
          [
            -1283.2418870736806,
            -1619.0598646488625
          ],
          [
            -1283.2418870736806,
            -516.457139127458
          ]
        ]
      },
      {
        "join_sides": [
          2,
          1
        ],
        "joins": [
          8,
          12
        ],
        "points": [
          [
            -1283.2418870736806,
            791.542860872542
          ],
          [
            -1283.2418870736806,
            1303.5219629203743
          ],
          [
            -649.3970012325575,
            1303.5219629203743
          ]
        ]
      },
      {
        "join_sides": [
          0,
          2
        ],
        "joins": [
          15,
          12
        ],
        "points": [
          [
            -299.2737724940366,
            2093.48622323827
          ],
          [
            -299.2737724940366,
            1713.5219629203743
          ]
        ]
      },
      {
        "join_sides": [
          3,
          1
        ],
        "joins": [
          14,
          3
        ],
        "points": [
          [
            2342.461908035684,
            2839.082072594268
          ],
          [
            3025.1515717670063,
            2839.082072594268
          ]
        ]
      },
      {
        "join_sides": [
          2,
          0
        ],
        "joins": [
          12,
          14
        ],
        "points": [
          [
            842.5324534015631,
            1713.5219629203743
          ],
          [
            842.5324534015631,
            2435.462677757311
          ]
        ]
      },
      {
        "join_sides": [
          3,
          1
        ],
        "joins": [
          7,
          15
        ],
        "points": [
          [
            -2141.4403435613076,
            2350.840880057398
          ],
          [
            -1585.1505437555159,
            2350.840880057398
          ]
        ]
      },
      {
        "join_sides": [
          3,
          1
        ],
        "joins": [
          11,
          2
        ],
        "points": [
          [
            5491.250604347943,
            4584.7202625129175
          ],
          [
            6345.202049644982,
            4584.7202625129175
          ]
        ]
      },
      {
        "join_sides": [
          2,
          0
        ],
        "joins": [
          15,
          4
        ],
        "points": [
          [
            -747.0351456498186,
            3113.48622323827
          ],
          [
            -747.0351456498186,
            4216.551834096632
          ]
        ]
      },
      {
        "join_sides": [
          2,
          1
        ],
        "joins": [
          5,
          0
        ],
        "points": [
          [
            -881.2188522011229,
            -3290.4962137565144
          ],
          [
            -881.2188522011229,
            -2729.0554384135276
          ],
          [
            365.654591616634,
            -2729.0554384135276
          ]
        ]
      },
      {
        "join_sides": [
          0,
          2
        ],
        "joins": [
          6,
          0
        ],
        "points": [
          [
            930.2257524904417,
            -1659.4655323885613
          ],
          [
            930.2257524904417,
            -2221.0554384135276
          ]
        ]
      },
      {
        "join_sides": [
          3,
          1
        ],
        "joins": [
          0,
          9
        ],
        "points": [
          [
            1753.654591616634,
            -2525.4211730343677
          ],
          [
            2626.29082169954,
            -2525.4211730343677
          ]
        ]
      },
      {
        "join_sides": [
          3,
          2
        ],
        "joins": [
          12,
          13
        ],
        "points": [
          [
            986.6029987674425,
            1303.5219629203743
          ],
          [
            2906.479761455227,
            1303.5219629203743
          ],
          [
            2906.479761455227,
            474.7225780818236
          ]
        ]
      }
    ],
    "rooms": [
      {
        "corridors": [
          [],
          [
            0,
            11
          ],
          [
            12
          ],
          [
            13
          ]
        ],
        "inter": false,
        "l": 1016.0,
        "main": true,
        "w": 1388.0,
        "x": 1059.654591616634,
        "y": -2729.0554384135276
      },
      {
        "corridors": [
          [],
          [],
          [],
          [
            0,
            2
          ]
        ],
        "inter": false,
        "l": 904.0,
        "main": true,
        "w": 1716.0,
        "x": -4254.639930012873,
        "y": -2129.6406566096093
      },
      {
        "corridors": [
          [],
          [
            9
          ],
          [],
          []
        ],
        "inter": false,
        "l": 964.0,
        "main": false,
        "w": 864.0,
        "x": 6777.202049644982,
        "y": 4837.418131295229
      },
      {
        "corridors": [
          [],
          [
            6
          ],
          [
            1
          ],
          []
        ],
        "inter": false,
        "l": 1104.0,
        "main": true,
        "w": 892.0,
        "x": 3471.1515717670063,
        "y": 3142.701467431225
      },
      {
        "corridors": [
          [
            10
          ],
          [],
          [],
          []
        ],
        "inter": false,
        "l": 520.0,
        "main": false,
        "w": 1160.0,
        "x": -504.9197475441213,
        "y": 4476.551834096632
      },
      {
        "corridors": [
          [],
          [],
          [
            11
          ],
          []
        ],
        "inter": false,
        "l": 620.0,
        "main": false,
        "w": 1076.0,
        "x": -881.2188522011229,
        "y": -3600.4962137565144
      },
      {
        "corridors": [
          [
            12
          ],
          [],
          [],
          []
        ],
        "inter": false,
        "l": 1344.0,
        "main": false,
        "w": 640.0,
        "x": 426.7969133642492,
        "y": -987.4655323885613
      },
      {
        "corridors": [
          [],
          [],
          [],
          [
            8
          ]
        ],
        "inter": false,
        "l": 752.0,
        "main": true,
        "w": 1260.0,
        "x": -2771.4403435613076,
        "y": 2232.195536876526
      },
      {
        "corridors": [
          [
            3
          ],
          [],
          [
            4
          ],
          []
        ],
        "inter": false,
        "l": 1308.0,
        "main": true,
        "w": 712.0,
        "x": -1283.2418870736806,
        "y": 137.54286087254198
      },
      {
        "corridors": [
          [],
          [
            13
          ],
          [],
          []
        ],
        "inter": false,
        "l": 632.0,
        "main": false,
        "w": 1336.0,
        "x": 3294.29082169954,
        "y": -2513.7869076552074
      },
      {
        "corridors": [
          [],
          [],
          [
            2
          ],
          [
            3
          ]
        ],
        "inter": false,
        "l": 632.0,
        "main": true,
        "w": 1716.0,
        "x": -2431.439048201214,
        "y": -1619.0598646488625
      },
      {
        "corridors": [
          [],
          [
            1
          ],
          [],
          [
            9
          ]
        ],
        "inter": false,
        "l": 1024.0,
        "main": true,
        "w": 1008.0,
        "x": 4987.250604347943,
        "y": 4302.022393730606
      },
      {
        "corridors": [
          [],
          [
            4
          ],
          [
            5,
            7
          ],
          [
            14
          ]
        ],
        "inter": false,
        "l": 820.0,
        "main": true,
        "w": 1636.0,
        "x": 168.6029987674425,
        "y": 1303.5219629203743
      },
      {
        "corridors": [
          [],
          [],
          [
            14
          ],
          []
        ],
        "inter": false,
        "l": 1652.0,
        "main": false,
        "w": 528.0,
        "x": 2906.479761455227,
        "y": -351.2774219181764
      },
      {
        "corridors": [
          [
            7
          ],
          [],
          [],
          [
            6
          ]
        ],
        "inter": false,
        "l": 652.0,
        "main": true,
        "w": 1644.0,
        "x": 1520.4619080356838,
        "y": 2761.462677757311
      },
      {
        "corridors": [
          [
            5
          ],
          [
            8
          ],
          [
            10
          ],
          []
        ],
        "inter": false,
        "l": 1020.0,
        "main": true,
        "w": 1176.0,
        "x": -997.1505437555159,
        "y": 2603.48622323827
      }
    ]
  },
  "model_type": "tinykeep",
  "vrf_inputs": {
    "alpha": "1:1:11e97f1da27b8cfe:arena_size=2048.0,corridor_redundancy=15.0,flock_factor=600.0,main_room_thresh=0.8,min_separation_factor=1.7,model=tinykeep,room_szmax=1024.0,room_szmin=512.0,room_szratio=1.8,rooms=16,tan_fudge=0.0001,tile_snap_size=4.0",
    "beta": "4ceba35be306324c2cb24182ae83a7d2926faed42ddf648bc74e4d3a5be1b1302f73c0efa3fd2431a0dd0944e55b73b7c5b998e84a7d4fcd5967f2129af9d49f",
    "pi": "65c7fb7fc147e77cf4701aea113f8ad19fd96dbb60912d91db4c6597a0b5dd9ba9f49dfccab55433ac52f5e114022b160ce6758cd9bf8d406661e1118376cfed90358e4ef391cb75cdaa155ce9838603",
    "public_key": "82fb81f632c50aef9e26ae16f6e9b716bb15f2603567f5e9db40ee3e8729fb2a",
    "secret": "960b89e5d183b25fc39bd8e609fe1381ad31ab7082e1bc43d2e08ae9ce50ac97",
    "seed": "11e97f1da27b8cfe"
  }
}